runai_streamer/__init__.py
runai_streamer/file_streamer/__init__.py
runai_streamer/file_streamer/file_streamer.py
runai_streamer/file_streamer/requests_iterator.py
runai_streamer/file_streamer/tests/__init__.py
runai_streamer/file_streamer/tests/test_file_streamer.py
runai_streamer/file_streamer/tests/test_requests_iterator.py
runai_streamer/libstreamer/__init__.py
runai_streamer/libstreamer/libstreamer.py
runai_streamer/libstreamer/lib/libstreamer.so
runai_streamer/libstreamer/tests/__init__.py
runai_streamer/libstreamer/tests/test_libstreamer.py
runai_streamer/safetensors_streamer/__init__.py
runai_streamer/safetensors_streamer/safetensors_pytorch.py
runai_streamer/safetensors_streamer/safetensors_streamer.py
runai_streamer/safetensors_streamer/tests/__init__.py
runai_streamer/safetensors_streamer/tests/test_safetensors_streamer.py
runai_streamer-0.4.1.dist-info/METADATA
runai_streamer-0.4.1.dist-info/WHEEL
runai_streamer-0.4.1.dist-info/top_level.txt
runai_streamer-0.4.1.dist-info/RECORD
