Metadata-Version: 2.1
Name: runai-streamer
Version: 0.4.1
Summary: UNKNOWN
Home-page: UNKNOWN
License: UNKNOWN
Platform: UNKNOWN
Requires-Dist: humanize
Requires-Dist: torch (<3.0.0,>=2.0.0)
Provides-Extra: s3
Requires-Dist: runai-streamer-s3 (==0.4.1) ; extra == 's3'
